{"id": "8Mc3jIsAAAAJ", "citedby": 1344, "citedby5y": 1129, "hindex": 12, "hindex5y": 12, "i10index": 14, "i10index5y": 13, "coauthors": [{"id": "yGLZpykAAAAJ", "name": "Jaime Grutzendler", "affiliation": "Professor of Neurology and Neuroscience, Yale University"}, {"id": "YcukH8YAAAAJ", "name": "Akiko Nishiyama", "affiliation": "Professor of Physiology and Neurobiology, University of Connecticut at Storrs"}, {"id": "vVYv77kAAAAJ", "name": "Kiran D Patel", "affiliation": "Postdoc, Yale University"}, {"id": "AB7TjyUAAAAJ", "name": "Lei Tong", "affiliation": "Yale University"}, {"id": "ktq2VUMAAAAJ", "name": "Peng YUAN", "affiliation": "Stanford University"}, {"id": "VYn72bsAAAAJ", "name": "Eyiyemisi Damisah", "affiliation": "Neurosurgery, Yale University"}, {"id": "mJNamLEAAAAJ", "name": "Aaron Schain", "affiliation": "Postdoctoral Fellow, BIDMC, Harvard University"}, {"id": "57vNcSIAAAAJ", "name": "Christopher Gon\u00e7alves", "affiliation": "Teacher Candidate, East Hartford High School"}, {"id": "eTxXN_EAAAAJ", "name": "Amin Sherafat", "affiliation": "Department of Physiology and Neurobiology, University of Connecticut"}, {"id": "cmqewL4AAAAJ", "name": "Alex Kwan", "affiliation": "Yale School of Medicine"}, {"id": "rQF-6HYAAAAJ", "name": "Fuyi Chen", "affiliation": "Yale University"}, {"id": "yHw-fi4AAAAJ", "name": "Maximilian Joesch", "affiliation": "IST Austria"}, {"id": "TmraWk0AAAAJ", "name": "Marc Takeno", "affiliation": "Research Scientist, Allen Institute for Brain Science"}, {"id": "dlV-qnUAAAAJ", "name": "Walter Scheirer", "affiliation": "Assistant Professor, University of Notre Dame"}, {"id": "PclBFdMAAAAJ", "name": "Hongkui Zeng", "affiliation": "Executive Vice President, Director of Allen Institute for Brain Science"}, {"id": "-yrazx4AAAAJ", "name": "Narayanan Kasthuri", "affiliation": "University of Chicago"}, {"id": "4mf8n7UAAAAJ", "name": "Rafael Vescovi", "affiliation": "University of Chicago"}], "name": "Robert Hill", "affiliation": "Assistant Professor, Dartmouth College", "interests": ["neuroscience", "neuron-glia interactions", "glial biology"], "cites_per_year": {"2009": 6, "2010": 11, "2011": 24, "2012": 32, "2013": 44, "2014": 93, "2015": 88, "2016": 186, "2017": 189, "2018": 239, "2019": 291, "2020": 133}, "publications": [{"bib": {"title": "Regional blood flow in the normal and ischemic brain is controlled by arteriolar smooth muscle cell contractility and not by capillary pericytes", "year": "2015"}, "source": "citations", "id_citations": "8Mc3jIsAAAAJ:PELIpwtuRlgC", "citedby": "320"}, {"bib": {"title": "Age-dependent fate and lineage restriction of single NG2 cells", "year": "2011"}, "source": "citations", "id_citations": "8Mc3jIsAAAAJ:u-x6o8ySG0sC", "citedby": "297"}, {"bib": {"title": "NG2 cells generate oligodendrocytes and gray matter astrocytes in the spinal cord", "year": "2008"}, "source": "citations", "id_citations": "8Mc3jIsAAAAJ:u5HHmVD_uO8C", "citedby": "134"}, {"bib": {"title": "Label-free in vivo imaging of myelinated axons in health and disease with spectral confocal reflectance microscopy", "year": "2014"}, "source": "citations", "id_citations": "8Mc3jIsAAAAJ:AXPGKjj_ei8C", "citedby": "102"}, {"bib": {"title": "Modulation of oligodendrocyte generation during a critical temporal window after NG2 cell division", "year": "2014"}, "source": "citations", "id_citations": "8Mc3jIsAAAAJ:tkaPQYYpVKoC", "citedby": "99"}, {"bib": {"title": "NG2 cells in white matter but not gray matter proliferate in response to PDGF", "year": "2013"}, "source": "citations", "id_citations": "8Mc3jIsAAAAJ:qjMakFHDy7sC", "citedby": "98"}, {"bib": {"title": "Lifelong cortical myelin plasticity and age-related degeneration in the live mammalian brain", "year": "2018"}, "source": "citations", "id_citations": "8Mc3jIsAAAAJ:JQOojiI6XY0C", "citedby": "90"}, {"bib": {"title": "NG2 cells (polydendrocytes): listeners to the neural network with diverse properties", "year": "2014"}, "source": "citations", "id_citations": "8Mc3jIsAAAAJ:eMMeJKvmdy0C", "citedby": "68"}, {"bib": {"title": "In vivo imaging of oligodendrocytes with sulforhodamine 101", "year": "2014"}, "source": "citations", "id_citations": "8Mc3jIsAAAAJ:_B80troHkn4C", "citedby": "38"}, {"bib": {"title": "A fluoro-Nissl dye identifies pericytes as distinct vascular mural cells during in vivo brain imaging", "year": "2017"}, "source": "citations", "id_citations": "8Mc3jIsAAAAJ:5awf1xo2G04C", "citedby": "30"}, {"bib": {"title": "Targeted two-photon chemical apoptotic ablation of defined cell types in vivo", "year": "2017"}, "source": "citations", "id_citations": "8Mc3jIsAAAAJ:ye4kPcJQO24C", "citedby": "16"}, {"bib": {"title": "Organotypic slice cultures to study oligodendrocyte dynamics and myelination", "year": "2014"}, "source": "citations", "id_citations": "8Mc3jIsAAAAJ:Y5dfb0dijaUC", "citedby": "14"}, {"bib": {"title": "Age-dependent decline in fate switch from NG2 cells to astrocytes after Olig2 deletion", "year": "2018"}, "source": "citations", "id_citations": "8Mc3jIsAAAAJ:VL0QpB8kHFEC", "citedby": "11"}, {"bib": {"title": "NG2 cells are uniformly distributed and NG2 is not required for barrel formation in the somatosensory cortex", "year": "2011"}, "source": "citations", "id_citations": "8Mc3jIsAAAAJ:d1gkVwhDpl0C", "citedby": "10"}, {"bib": {"title": "Flexible learning-free segmentation and reconstruction of neural volumes", "year": "2018"}, "source": "citations", "id_citations": "8Mc3jIsAAAAJ:_Ybze24A_UAC", "citedby": "6"}, {"bib": {"title": "Uncovering the biology of myelin with optical imaging of the live brain", "year": "2019"}, "source": "citations", "id_citations": "8Mc3jIsAAAAJ:W5xh706n7nkC", "citedby": "4"}, {"bib": {"title": "Do short-term changes in white matter structure indicate learning-induced myelin plasticity?", "year": "2013"}, "source": "citations", "id_citations": "8Mc3jIsAAAAJ:Mojj43d5GZwC", "citedby": "3"}, {"bib": {"title": "Myelin plasticity in adulthood and aging", "year": "2020"}, "source": "citations", "id_citations": "8Mc3jIsAAAAJ:Fu2w8maKXqMC", "citedby": "2"}, {"bib": {"title": "Organotypic slice cultures to study oligodendrocyte proliferation, fate, and myelination", "year": "2018"}, "source": "citations", "id_citations": "8Mc3jIsAAAAJ:uLbwQdceFCQC", "citedby": "2"}, {"bib": {"title": "Aberrant axonal pathfinding and exuberant myelination in an inducible model of neocortical heterotopia", "year": "2020"}, "source": "citations", "id_citations": "8Mc3jIsAAAAJ:kzcrU_BdoSEC", "citedby": "0"}, {"bib": {"title": "Flexible Learning-Free Segmentation and Reconstruction for Sparse Neuronal Circuit Tracing", "year": "2018"}, "source": "citations", "id_citations": "8Mc3jIsAAAAJ:NJ774b8OgUMC", "citedby": "0"}]}