{"id": "oIbxZhIAAAAJ", "citedby": 4184, "citedby5y": 1618, "hindex": 37, "hindex5y": 22, "i10index": 59, "i10index5y": 42, "coauthors": [{"id": "vVdRxtUAAAAJ", "name": "Jun Ueda", "affiliation": "Mechanical Engineering, Georgia Institute of Technology"}, {"id": "qZLQp6UAAAAJ", "name": "Mark Latash", "affiliation": "Professor of Kinesiology, The Pennsylvania State University"}, {"id": "J1FNYIEAAAAJ", "name": "Vladimir Zatsiorsky", "affiliation": "Pennsylvania State University"}, {"id": "svaTGrwAAAAJ", "name": "Karim G. Sabra", "affiliation": "Georgia Institute of Technology"}, {"id": "jEeqcnYAAAAJ", "name": "Kei Masani", "affiliation": "Motion & Adaptation Science Laboratory"}, {"id": "92JpqKoAAAAJ", "name": "Keenan KG", "affiliation": "University of Wisconsin - Milwaukee"}, {"id": "2jKXzt8AAAAJ", "name": "Yuichi Kurita", "affiliation": "Hiroshima University"}, {"id": "mZ1fx9kAAAAJ", "name": "Evangelos A. Christou", "affiliation": "Professor, Applied Physiology and Kinesiology, University of Florida"}, {"id": "J4JEFLQAAAAJ", "name": "Sheng Li, M.D., Ph.D.", "affiliation": "University of Texas Health Science Center - Houston; TIRR Memorial Hermann Hospital"}, {"id": "XCLOinIAAAAJ", "name": "Mike Pascoe, PhD", "affiliation": "Assistant Professor of Anatomy, University of Colorado Anschutz Medical Campus"}, {"id": "wXCQ9OIAAAAJ", "name": "Ming Ding", "affiliation": "Nagoya University"}, {"id": "Vc0Z600AAAAJ", "name": "Mathias Fink", "affiliation": "Institut Langevin, ESPCI Paris, CNRS"}, {"id": "Z_kEGKcAAAAJ", "name": "Lewis A. Wheaton", "affiliation": "Associate Professor, School of Biological Sciences, Georgia Tech"}, {"id": "7hhNHI0AAAAJ", "name": "Andrew J. Butler", "affiliation": "Professor of Physical Therapy, Georgia State University"}, {"id": "vYxhKTAAAAAJ", "name": "Melih Turkseven", "affiliation": "Georgia Institute of Technology"}, {"id": "-eUEfV0AAAAJ", "name": "Maysam Ghovanloo", "affiliation": "CTO, Bionic Sciences Inc."}, {"id": "8uxdWPYAAAAJ", "name": "karen s\u00f8gaard", "affiliation": "Professor i fysiologi p\u00e5 Syddansk Universitet"}, {"id": "AQH055QAAAAJ", "name": "Xueliang Huo", "affiliation": "IEB, Microsoft"}, {"id": "vcGE7aIAAAAJ", "name": "William Gallagher", "affiliation": "NASA Goddard Space Flight Center"}, {"id": "a_S5LA0AAAAJ", "name": "Jae Kun Shim", "affiliation": "Professor of Kinesiology, Bioengineering, Neuroscience, University of Maryland"}], "name": "Minoru \"Shino\" Shinohara", "affiliation": "Biological Sciences, Georgia Institute of Technology", "interests": ["Neuromuscular Physiology of Human Motor Control"], "cites_per_year": {"1997": 14, "1998": 11, "1999": 18, "2000": 35, "2001": 44, "2002": 55, "2003": 76, "2004": 97, "2005": 141, "2006": 201, "2007": 155, "2008": 185, "2009": 200, "2010": 230, "2011": 217, "2012": 253, "2013": 270, "2014": 272, "2015": 254, "2016": 273, "2017": 317, "2018": 343, "2019": 321, "2020": 109}, "publications": [{"bib": {"title": "Oxygen availability and motor unit activity in humans", "year": "1992"}, "source": "citations", "id_citations": "oIbxZhIAAAAJ:u5HHmVD_uO8C", "citedby": "268"}, {"bib": {"title": "Efficacy of tourniquet ischemia for strength training with low resistance", "year": "1997"}, "source": "citations", "id_citations": "oIbxZhIAAAAJ:TQgYirikUcIC", "citedby": "235"}, {"bib": {"title": "Real\u2010time visualization of muscle stiffness distribution with ultrasound shear wave imaging during muscle contraction", "year": "2010"}, "source": "citations", "id_citations": "oIbxZhIAAAAJ:W7OEmFMy1HYC", "citedby": "187"}, {"bib": {"title": "Increase in neuromuscular activity and oxygen uptake during heavy exercise", "year": "1992"}, "source": "citations", "id_citations": "oIbxZhIAAAAJ:R3hNpaxXUhUC", "citedby": "175"}, {"bib": {"title": "Effects of age and gender on finger coordination in MVC and submaximal force-matching tasks", "year": "2003"}, "source": "citations", "id_citations": "oIbxZhIAAAAJ:u-x6o8ySG0sC", "citedby": "152"}, {"bib": {"title": "Learning multi-finger synergies: an uncontrolled manifold analysis", "year": "2004"}, "source": "citations", "id_citations": "oIbxZhIAAAAJ:d1gkVwhDpl0C", "citedby": "148"}, {"bib": {"title": "Decrease in maximal voluntary contraction by tonic vibration applied to a single synergist muscle in humans", "year": "2000"}, "source": "citations", "id_citations": "oIbxZhIAAAAJ:2osOgNQ5qMEC", "citedby": "128"}, {"bib": {"title": "Finger interaction during accurate multi-finger force production tasks in young and elderly persons", "year": "2004"}, "source": "citations", "id_citations": "oIbxZhIAAAAJ:9yKSN-GCB0IC", "citedby": "125"}, {"bib": {"title": "Age effects on force produced by intrinsic and extrinsic hand muscles and finger interaction during MVC tasks", "year": "2003"}, "source": "citations", "id_citations": "oIbxZhIAAAAJ:IjCSPb-OGe4C", "citedby": "116"}, {"bib": {"title": "Steadiness in plantar flexor muscles and its relation to postural sway in young and elderly adults", "year": "2010"}, "source": "citations", "id_citations": "oIbxZhIAAAAJ:-f6ydRqryjwC", "citedby": "108"}, {"bib": {"title": "Characteristics of surface mechanomyogram are dependent on development of fusion of motor units in humans", "year": "2002"}, "source": "citations", "id_citations": "oIbxZhIAAAAJ:UeHWp8X0CEIC", "citedby": "108"}, {"bib": {"title": "Individual muscle control using an exoskeleton robot for muscle function testing", "year": "2010"}, "source": "citations", "id_citations": "oIbxZhIAAAAJ:mB3voiENLucC", "citedby": "106"}, {"bib": {"title": "Non-uniform mechanical activity of quadriceps muscle during fatigue by repeated maximal voluntary contraction in humans", "year": "1999"}, "source": "citations", "id_citations": "oIbxZhIAAAAJ:Tyk-4Ss8FVUC", "citedby": "104"}, {"bib": {"title": "Muscle shear modulus measured with ultrasound shear\u2010wave elastography across a wide range of contraction intensity", "year": "2014"}, "source": "citations", "id_citations": "oIbxZhIAAAAJ:Zph67rFs4hoC", "citedby": "101"}, {"bib": {"title": "Effects of prolonged vibration on motor unit activity and motor performance", "year": "2005"}, "source": "citations", "id_citations": "oIbxZhIAAAAJ:UebtZRa9Y70C", "citedby": "101"}, {"bib": {"title": "Alternate muscle activity observed between knee extensor synergists during low-level sustained contractions", "year": "2002"}, "source": "citations", "id_citations": "oIbxZhIAAAAJ:qjMakFHDy7sC", "citedby": "99"}, {"bib": {"title": "Fluctuations in acceleration during voluntary contractions lead to greater impairment of movement accuracy in old adults", "year": "2003"}, "source": "citations", "id_citations": "oIbxZhIAAAAJ:0EnyYjriUFMC", "citedby": "93"}, {"bib": {"title": "Mechanomyography of the human quadriceps muscle during incremental cycle ergometry", "year": "1997"}, "source": "citations", "id_citations": "oIbxZhIAAAAJ:Y0pCki6q_DkC", "citedby": "92"}, {"bib": {"title": "Muscle activation and time to task failure differ with load type and contraction intensity for a human hand muscle", "year": "2005"}, "source": "citations", "id_citations": "oIbxZhIAAAAJ:YsMSGLbcyi4C", "citedby": "85"}, {"bib": {"title": "The ventilatory threshold gives maximal lactate steady state", "year": "1991"}, "source": "citations", "id_citations": "oIbxZhIAAAAJ:r0BpntZqJG4C", "citedby": "80"}, {"bib": {"title": "Prolonged muscle vibration increases stretch reflex amplitude, motor unit discharge rate, and force fluctuations in a hand muscle", "year": "2005"}, "source": "citations", "id_citations": "oIbxZhIAAAAJ:5nxA0vEk-isC", "citedby": "76"}, {"bib": {"title": "Mechanomyogram from the different heads of the quadriceps muscle during incremental knee extension", "year": "1998"}, "source": "citations", "id_citations": "oIbxZhIAAAAJ:zYLM7Y9cAGgC", "citedby": "76"}, {"bib": {"title": "Strength training counteracts motor performance losses during bed rest", "year": "2003"}, "source": "citations", "id_citations": "oIbxZhIAAAAJ:WF5omc3nYNoC", "citedby": "75"}, {"bib": {"title": "Quantification of dry needling and posture effects on myofascial trigger points using ultrasound shear-wave elastography", "year": "2013"}, "source": "citations", "id_citations": "oIbxZhIAAAAJ:Wp0gIr-vW9MC", "citedby": "69"}, {"bib": {"title": "A single bout of resistance exercise can enhance episodic memory performance", "year": "2014"}, "source": "citations", "id_citations": "oIbxZhIAAAAJ:_B80troHkn4C", "citedby": "68"}, {"bib": {"title": "Contralateral activity in a homologous hand muscle during voluntary contractions is greater in old adults", "year": "2003"}, "source": "citations", "id_citations": "oIbxZhIAAAAJ:eQOLeE2rZwMC", "citedby": "64"}, {"bib": {"title": "The frequency of alternate muscle activity is associated with the attenuation in muscle fatigue", "year": "2006"}, "source": "citations", "id_citations": "oIbxZhIAAAAJ:7PzlFSSx8tAC", "citedby": "62"}, {"bib": {"title": "Acute decrease in the stiffness of resting muscle belly due to static stretching", "year": "2015"}, "source": "citations", "id_citations": "oIbxZhIAAAAJ:70eg2SAEIzsC", "citedby": "61"}, {"bib": {"title": "Force fluctuations are modulated by alternate muscle activity of knee extensor synergists during low-level sustained contraction", "year": "2004"}, "source": "citations", "id_citations": "oIbxZhIAAAAJ:9ZlFYXVOiuMC", "citedby": "61"}, {"bib": {"title": "Comparison of sympatho-vagal function among diabetic patients, normal controls and endurance athletes by heart rate spectral analysis", "year": "1993"}, "source": "citations", "id_citations": "oIbxZhIAAAAJ:2P1L_qKh6hAC", "citedby": "55"}, {"bib": {"title": "Fluctuations in plantar flexion force are reduced after prolonged tendon vibration", "year": "2004"}, "source": "citations", "id_citations": "oIbxZhIAAAAJ:ufrVoPGSRksC", "citedby": "54"}, {"bib": {"title": "Nonlinear time-course of lumbar muscle fatigue using recurrence quantifications", "year": "2000"}, "source": "citations", "id_citations": "oIbxZhIAAAAJ:mVmsd5A6BfQC", "citedby": "52"}, {"bib": {"title": "Wearable sensorimotor enhancer for fingertip based on stochastic resonance effect", "year": "2013"}, "source": "citations", "id_citations": "oIbxZhIAAAAJ:qUcmZB5y_30C", "citedby": "49"}, {"bib": {"title": "Mechanomyography for studying force fluctuations and muscle fatigue", "year": "2006"}, "source": "citations", "id_citations": "oIbxZhIAAAAJ:hqOjcs7Dif8C", "citedby": "46"}, {"bib": {"title": "Corticomuscular coherence with and without additional task in the elderly", "year": "2012"}, "source": "citations", "id_citations": "oIbxZhIAAAAJ:YOwf2qJgpHMC", "citedby": "43"}, {"bib": {"title": "Sympatho-vagal activities of NIDDM patients during exercise as determined by heart rate spectral analysis", "year": "1995"}, "source": "citations", "id_citations": "oIbxZhIAAAAJ:b0M2c_1WBrUC", "citedby": "40"}, {"bib": {"title": "Effect of local blood circulation and absolute torque on muscle endurance at two different knee-joint angles in humans", "year": "2001"}, "source": "citations", "id_citations": "oIbxZhIAAAAJ:QIV2ME_5wuYC", "citedby": "38"}, {"bib": {"title": "Attenuation of corticomuscular coherence with additional motor or non-motor task", "year": "2011"}, "source": "citations", "id_citations": "oIbxZhIAAAAJ:3fE2CSJIrl8C", "citedby": "35"}, {"bib": {"title": "Local blood circulation among knee extensor synergists in relation to alternate muscle activity during low-level sustained contraction", "year": "2003"}, "source": "citations", "id_citations": "oIbxZhIAAAAJ:dhFuZR0502QC", "citedby": "35"}, {"bib": {"title": "Changes in muscle sympathetic nerve activity and calf blood flow during combined leg and forearm exercise", "year": "1992"}, "source": "citations", "id_citations": "oIbxZhIAAAAJ:maZDTaKrznsC", "citedby": "30"}, {"bib": {"title": "Exhausting handgrip exercise reduces the blood flow in the active calf muscle exercising at low intensity", "year": "1994"}, "source": "citations", "id_citations": "oIbxZhIAAAAJ:isC4tDSrTZIC", "citedby": "27"}, {"bib": {"title": "Wearable sensorimotor enhancer for a fingertip based on stochastic resonance", "year": "2011"}, "source": "citations", "id_citations": "oIbxZhIAAAAJ:IWHjjKOFINEC", "citedby": "26"}, {"bib": {"title": "Alterations in synergistic muscle activation impact fluctuations in net force", "year": "2009"}, "source": "citations", "id_citations": "oIbxZhIAAAAJ:LkGwnXOMwfcC", "citedby": "26"}, {"bib": {"title": "Biarticular leg muscles and links to running economy", "year": "2008"}, "source": "citations", "id_citations": "oIbxZhIAAAAJ:k_IJM867U9cC", "citedby": "26"}, {"bib": {"title": "Fluctuations in motor output during steady contractions are weakly related across contraction types and between hands", "year": "2005"}, "source": "citations", "id_citations": "oIbxZhIAAAAJ:8k81kl-MbHgC", "citedby": "25"}, {"bib": {"title": "Modulation of muscle activity and force fluctuations in the plantarflexors after bedrest depends on knee position", "year": "2007"}, "source": "citations", "id_citations": "oIbxZhIAAAAJ:_FxGoFyzp5QC", "citedby": "24"}, {"bib": {"title": "The medial gastrocnemius muscle attenuates force fluctuations during plantar flexion", "year": "2006"}, "source": "citations", "id_citations": "oIbxZhIAAAAJ:roLk4NBRz8UC", "citedby": "23"}, {"bib": {"title": "Adaptations in motor unit behavior in elderly adults", "year": "2011"}, "source": "citations", "id_citations": "oIbxZhIAAAAJ:hFOr9nPyWt4C", "citedby": "21"}, {"bib": {"title": "Invariable H-reflex and sustained facilitation of stretch reflex with heightened sympathetic outflow", "year": "2009"}, "source": "citations", "id_citations": "oIbxZhIAAAAJ:HDshCWvjkbEC", "citedby": "21"}, {"bib": {"title": "Laser-detected lateral muscle displacement is correlated with force fluctuations during voluntary contractions in humans", "year": "2008"}, "source": "citations", "id_citations": "oIbxZhIAAAAJ:Se3iqnhoufwC", "citedby": "21"}, {"bib": {"title": "Oscillations in motor unit discharge are reflected in the low-frequency component of rectified surface EMG and the rate of change in force", "year": "2013"}, "source": "citations", "id_citations": "oIbxZhIAAAAJ:KlAtU1dfN6UC", "citedby": "19"}, {"bib": {"title": "Low\u2010frequency component of rectified EMG is temporally correlated with force and instantaneous rate of force fluctuations during steady contractions", "year": "2013"}, "source": "citations", "id_citations": "oIbxZhIAAAAJ:kNdYIx-mwKoC", "citedby": "19"}, {"bib": {"title": "Enhanced corticospinal excitability with physiologically heightened sympathetic nerve activity", "year": "2013"}, "source": "citations", "id_citations": "oIbxZhIAAAAJ:MXK_kJrjxJIC", "citedby": "18"}, {"bib": {"title": "Reliability of ultrasound shear-wave elastography in assessing low back musculature elasticity in asymptomatic individuals", "year": "2018"}, "source": "citations", "id_citations": "oIbxZhIAAAAJ:V3AGJWp-ZtQC", "citedby": "15"}, {"bib": {"title": "Propagation direction of natural mechanical oscillations in the biceps brachii muscle during voluntary contraction", "year": "2012"}, "source": "citations", "id_citations": "oIbxZhIAAAAJ:qxL8FJ1GzNcC", "citedby": "14"}, {"bib": {"title": "Changes in finger coordination and hand function with advanced age", "year": "2006"}, "source": "citations", "id_citations": "oIbxZhIAAAAJ:L8Ckcad2t8MC", "citedby": "11"}, {"bib": {"title": "Timing analysis of robotic neuromodulatory rehabilitation system for paired associative stimulation", "year": "2016"}, "source": "citations", "id_citations": "oIbxZhIAAAAJ:D_sINldO8mEC", "citedby": "10"}, {"bib": {"title": "Motor task planning for neuromuscular function tests using an individual muscle control technique", "year": "2009"}, "source": "citations", "id_citations": "oIbxZhIAAAAJ:4JMBOYKVnBMC", "citedby": "10"}, {"bib": {"title": "Muscle activation strategies in multiple muscle systems", "year": "2009"}, "source": "citations", "id_citations": "oIbxZhIAAAAJ:ZeXyd9-uunAC", "citedby": "10"}, {"bib": {"title": "Motor cortical disinhibition with baroreceptor unloading induced by orthostatic stress", "year": "2014"}, "source": "citations", "id_citations": "oIbxZhIAAAAJ:K3LRdlH-MEoC", "citedby": "9"}, {"bib": {"title": "Non-uniformity of muscle oxygenation in the quadriceps muscle during incremental knee extension", "year": "1999"}, "source": "citations", "id_citations": "oIbxZhIAAAAJ:iH-uZ7U-co4C", "citedby": "9"}, {"bib": {"title": "Correlated EMG oscillations between antagonists during cocontraction in men", "year": "2017"}, "source": "citations", "id_citations": "oIbxZhIAAAAJ:BrmTIyaxlBUC", "citedby": "8"}, {"bib": {"title": "Assessment of muscle stiffness using a continuously scanning laser\u2010Doppler vibrometer", "year": "2014"}, "source": "citations", "id_citations": "oIbxZhIAAAAJ:aqlVkmm33-oC", "citedby": "7"}, {"bib": {"title": "Robotic rehabilitation exercise in hemiparetic limbs based on functional synchronization of voluntary and involuntary nerve impulses", "year": "2014"}, "source": "citations", "id_citations": "oIbxZhIAAAAJ:fQNAKQ3IYiAC", "citedby": "6"}, {"bib": {"title": "Control of voluntary and involuntary nerve impulses for hemiparesis rehabilitation and MRI study", "year": "2013"}, "source": "citations", "id_citations": "oIbxZhIAAAAJ:Tiz5es2fbqcC", "citedby": "6"}, {"bib": {"title": "Identifying the source of radial nerve afferents that inhibit biceps brachii", "year": "2006"}, "source": "citations", "id_citations": "oIbxZhIAAAAJ:SdhP9T11ey4C", "citedby": "5"}, {"bib": {"title": "The changes in EMG and steadiness with variation in movement speed differ for concentric and eccentric contractions", "year": "2001"}, "source": "citations", "id_citations": "oIbxZhIAAAAJ:f2IySw72cVMC", "citedby": "5"}, {"bib": {"title": "Slow Intermuscular Oscillations are Associated with Cocontraction Steadiness.", "year": "2017"}, "source": "citations", "id_citations": "oIbxZhIAAAAJ:eflP2zaiRacC", "citedby": "4"}, {"bib": {"title": "Unloading muscle activation enhances force perception", "year": "2014"}, "source": "citations", "id_citations": "oIbxZhIAAAAJ:eJXPG6dFmWUC", "citedby": "4"}, {"bib": {"title": "Motor performance of tongue with a computer-integrated system under different levels of background physical exertion", "year": "2013"}, "source": "citations", "id_citations": "oIbxZhIAAAAJ:M3ejUd6NZC8C", "citedby": "4"}, {"bib": {"title": "An improved human-robot interface by measurement of muscle stiffness", "year": "2012"}, "source": "citations", "id_citations": "oIbxZhIAAAAJ:e5wmG9Sq2KIC", "citedby": "4"}, {"bib": {"title": "Fluctuations in motor output of a hand muscle can be altered by the mechanical properties of the position sensor", "year": "2008"}, "source": "citations", "id_citations": "oIbxZhIAAAAJ:_Qo2XoVZTnwC", "citedby": "4"}, {"bib": {"title": "Robotic neuromuscular facilitation for regaining neural activation in hemiparetic limbs", "year": "2015"}, "source": "citations", "id_citations": "oIbxZhIAAAAJ:VOx2b1Wkg3QC", "citedby": "3"}, {"bib": {"title": "Effects of additional workload on hand and tongue performance", "year": "2010"}, "source": "citations", "id_citations": "oIbxZhIAAAAJ:4TOpqqG69KYC", "citedby": "3"}, {"bib": {"title": "Coactivation of hand muscles and movement fluctuations in old adults", "year": "2007"}, "source": "citations", "id_citations": "oIbxZhIAAAAJ:BqipwSGYUEgC", "citedby": "3"}, {"bib": {"title": "Small Lateral Displacement of the Muscle Represents Low-Frequency Force Fluctuations During Voluntary Contractions in Humans: 2430Board# 162 9: 30 AM\u201310: 30 AM", "year": "2006"}, "source": "citations", "id_citations": "oIbxZhIAAAAJ:dfsIfKJdRG4C", "citedby": "3"}, {"bib": {"title": "Reduced slow component of oxygen uptake by endurance training is associated with reduced muscle deoxygenation", "year": "2001"}, "source": "citations", "id_citations": "oIbxZhIAAAAJ:LPZeul_q3PIC", "citedby": "3"}, {"bib": {"title": "Normative parameters and anthropometric variability of lumbar muscle stiffness using ultrasound shear-wave elastography", "year": "2019"}, "source": "citations", "id_citations": "oIbxZhIAAAAJ:5ugPr518TE4C", "citedby": "2"}, {"bib": {"title": "Automatic analysis of ultrasound shear-wave elastography in skeletal muscle without non-contractile tissue contamination", "year": "2018"}, "source": "citations", "id_citations": "oIbxZhIAAAAJ:wbdj-CoPYUoC", "citedby": "2"}, {"bib": {"title": "Optimal inter-stimulus interval for paired associative stimulation with mechanical stimulation", "year": "2017"}, "source": "citations", "id_citations": "oIbxZhIAAAAJ:1qzjygNMrQYC", "citedby": "2"}, {"bib": {"title": "Exercise-Induced Alteration in Brain Activity during Motor Performance under Cognitive Stress", "year": "2014"}, "source": "citations", "id_citations": "oIbxZhIAAAAJ:Y5dfb0dijaUC", "citedby": "2"}, {"bib": {"title": "Comparison of Ultrasound Muscle Stiffness Measurement and Electromyography Towards Validation of an Algorithm for Individual Muscle Control", "year": "2013"}, "source": "citations", "id_citations": "oIbxZhIAAAAJ:WbkHhVStYXYC", "citedby": "2"}, {"bib": {"title": "Effects of age and gender on finger coordination during force production tasks", "year": "2002"}, "source": "citations", "id_citations": "oIbxZhIAAAAJ:bnK-pcrLprsC", "citedby": "2"}, {"bib": {"title": "831 AUGMENTED MUSCULAR ACTIVATION FOR FORCE PRODUCTION DURING AND AFTER MAXIMAL INCREMENTAL EXERCISE", "year": "1993"}, "source": "citations", "id_citations": "oIbxZhIAAAAJ:rO6llkc54NcC", "citedby": "2"}, {"bib": {"title": "Corticospinal excitability for flexor carpi radialis decreases with baroreceptor unloading during intentional co-contraction with opposing forearm muscles", "year": "2019"}, "source": "citations", "id_citations": "oIbxZhIAAAAJ:1yQoGdGgb4wC", "citedby": "1"}, {"bib": {"title": "Robotic finger perturbation training improves finger postural steadiness and hand dexterity", "year": "2018"}, "source": "citations", "id_citations": "oIbxZhIAAAAJ:kRWSkSYxWN8C", "citedby": "1"}, {"bib": {"title": "Unpowered Sensorimotor-Enhancing Suit Reduces Muscle Activation and Improves Force Perception", "year": "2017"}, "source": "citations", "id_citations": "oIbxZhIAAAAJ:q3oQSFYPqjQC", "citedby": "1"}, {"bib": {"title": "Adaptive Human-Robot Physical Interaction for Robot Coworkers", "year": "2017"}, "source": "citations", "id_citations": "oIbxZhIAAAAJ:eMMeJKvmdy0C", "citedby": "1"}, {"bib": {"title": "Exercise-induced Dehydration Alters Brain Activation During A Cognitive-motor Task: 1836 Board# 181 May 28, 200 PM-330 PM", "year": "2015"}, "source": "citations", "id_citations": "oIbxZhIAAAAJ:5awf1xo2G04C", "citedby": "1"}, {"bib": {"title": "Stiffness Quantification of Human Calf Muscle During Standing Wall Stretching Using Ultrasound Shear-wave Elastography", "year": "2013"}, "source": "citations", "id_citations": "oIbxZhIAAAAJ:738O_yMBCRsC", "citedby": "1"}, {"bib": {"title": "Feature subset selection for age-related changes in EEG and EMG during motor tasks", "year": "2010"}, "source": "citations", "id_citations": "oIbxZhIAAAAJ:ULOm3_A8WrAC", "citedby": "1"}, {"bib": {"title": "Individual muscle control using an exoskeleton robot for muscle function testing", "year": "2009"}, "source": "citations", "id_citations": "oIbxZhIAAAAJ:_Ybze24A_UAC", "citedby": "1"}, {"bib": {"title": "1. Motor control of individual fingers", "year": "2009"}, "source": "citations", "id_citations": "oIbxZhIAAAAJ:ye4kPcJQO24C", "citedby": "1"}, {"bib": {"title": "Frequency Content Of Kinematic Signals Influences Measures Of Steadiness For A Hand Muscle: 863 Board# 85 9: 00 AM\u201310: 30 AM", "year": "2005"}, "source": "citations", "id_citations": "oIbxZhIAAAAJ:ZuybSZzF8UAC", "citedby": "1"}, {"bib": {"title": "Increased neuromuscular activity elicited by mild ischemia is associated with increased slow component of oxygen uptake", "year": "2001"}, "source": "citations", "id_citations": "oIbxZhIAAAAJ:B3FOqHPlNUQC", "citedby": "1"}, {"bib": {"title": "New trends for practice in telecommunication applied to preventive and environmental medicine", "year": "1997"}, "source": "citations", "id_citations": "oIbxZhIAAAAJ:j3f4tGmQtD8C", "citedby": "1"}, {"bib": {"title": "594 DIFFICULTIES WITH V-SLOPE METHOD FOR DETERMINING VENTILATORY THRESHOLD", "year": "1990"}, "source": "citations", "id_citations": "oIbxZhIAAAAJ:XiVPGOgt02cC", "citedby": "1"}, {"bib": {"title": "Power spectrum of heart rate fluctuations during incremental cycle exercise", "year": "1989"}, "source": "citations", "id_citations": "oIbxZhIAAAAJ:dTyEYWd-f8wC", "citedby": "1"}, {"bib": {"title": "Statistical Inter-stimulus Interval Window Estimation for Transient Neuromodulation via Paired Mechanical and Brain Stimulation", "year": "2020"}, "source": "citations", "id_citations": "oIbxZhIAAAAJ:W5xh706n7nkC", "citedby": "0"}, {"bib": {"title": "Lumbar muscle stiffness is different in individuals with low back pain than asymptomatic controls and is associated with pain and disability, but not common physical \u2026", "year": "2020"}, "source": "citations", "id_citations": "oIbxZhIAAAAJ:dQ2og3OwTAUC", "citedby": "0"}, {"bib": {"title": "Anti-phase cocontraction practice attenuates in-phase low-frequency oscillations between antagonistic muscles as assessed with phase coherence", "year": "2020"}, "source": "citations", "id_citations": "oIbxZhIAAAAJ:uLbwQdceFCQC", "citedby": "0"}, {"bib": {"title": "Preliminary Evaluation of a Tongue-Operated Exoskeleton for Post-Stroke Upper Limb Rehabilitation", "year": "2017"}, "source": "citations", "id_citations": "oIbxZhIAAAAJ:JoZmwDi-zQgC", "citedby": "0"}, {"bib": {"title": "Preface of the Section Focused on Superhuman Technology.", "year": "2017"}, "source": "citations", "id_citations": "oIbxZhIAAAAJ:mvPsJ3kp5DgC", "citedby": "0"}, {"bib": {"title": "RELIABILITY OF ULTRASOUND SHEAR-WAVE ELASTOGRAPHY IN MEASURING LOW BACK MUSCULATURE STIFFNESS IN ASYMPTOMATIC INDIVIDUALS: OPO106", "year": "2016"}, "source": "citations", "id_citations": "oIbxZhIAAAAJ:hkOj_22Ku90C", "citedby": "0"}, {"bib": {"title": "NORMATIVE PARAMETERS OF LUMBAR MUSCLE STIFFNESS USING ULTRASOUND SHEAR-WAVE ELASTOGRAPHY: OPO72", "year": "2016"}, "source": "citations", "id_citations": "oIbxZhIAAAAJ:WA5NYHcadZ8C", "citedby": "0"}, {"bib": {"title": "Muscle Stiffness Quantification With Novel Ultrasound Elastography Imaging During Fatiguing Contraction", "year": "2012"}, "source": "citations", "id_citations": "oIbxZhIAAAAJ:WqliGbK-hY8C", "citedby": "0"}, {"bib": {"title": "Muscle Stiffness Quantification With Novel Ultrasound Elastography Imaging For Detecting Muscle Damage After Eccentric Contractions", "year": "2012"}, "source": "citations", "id_citations": "oIbxZhIAAAAJ:AXPGKjj_ei8C", "citedby": "0"}, {"bib": {"title": "Insight into the Writing and Reviewing of Scientific Papers in English from the Standpoint of Journal Editor", "year": "2012"}, "source": "citations", "id_citations": "oIbxZhIAAAAJ:VL0QpB8kHFEC", "citedby": "0"}, {"bib": {"title": "measurement of human muscle stiffness and its application to effective human-robot interface design", "year": "2011"}, "source": "citations", "id_citations": "oIbxZhIAAAAJ:t6usbXjVLHcC", "citedby": "0"}, {"bib": {"title": "Noninvasive assessment of attention state from correlated oscillations in brain and muscle", "year": "2010"}, "source": "citations", "id_citations": "oIbxZhIAAAAJ:Mojj43d5GZwC", "citedby": "0"}, {"bib": {"title": "Eugene Y. Gaye\ufeff", "year": "2008"}, "source": "citations", "id_citations": "oIbxZhIAAAAJ:PR6Y55bgFSsC", "citedby": "0"}, {"bib": {"title": "Interaction between synergist muscles during voluntary contractions: 3983: 45 PM-4: 10 PM", "year": "2007"}, "source": "citations", "id_citations": "oIbxZhIAAAAJ:tkaPQYYpVKoC", "citedby": "0"}, {"bib": {"title": "Agonist-antagonist Coactivation Differs for Young and Old Adults During a Maximal Voluntary Contraction: 2417Board# 149 8: 30 AM\u20139: 30 AM", "year": "2006"}, "source": "citations", "id_citations": "oIbxZhIAAAAJ:LjlpjdlvIbIC", "citedby": "0"}, {"bib": {"title": "Relation Between Running Economy and Continuous Jumping Mechanical Power Measures: 8631: 15 PM\u20131: 30 PM", "year": "2006"}, "source": "citations", "id_citations": "oIbxZhIAAAAJ:9vf0nzSNQJEC", "citedby": "0"}, {"bib": {"title": "Activation of Gastrocnemii influences Steadiness in Plantarflexion Force", "year": "2004"}, "source": "citations", "id_citations": "oIbxZhIAAAAJ:5Ul4iDaHHb8C", "citedby": "0"}, {"bib": {"title": "Response to the letter of Quaresima and Ferrari\" More on the use of near-infrared spectroscopy to measure muscle oxygenation in humans\"", "year": "2003"}, "source": "citations", "id_citations": "oIbxZhIAAAAJ:M3NEmzRMIkIC", "citedby": "0"}, {"bib": {"title": "PROLONGED VIBRATION TO ACHILLES TENDON IMPROVES THE STEADINESS IN FORCE BY THE PLANTARFLEXOR MUSCLES", "year": "2003"}, "source": "citations", "id_citations": "oIbxZhIAAAAJ:8AbLer7MMksC", "citedby": "0"}, {"bib": {"title": "REDUCED SLOW COMPONENT OF OXYGEN UPTAKE BY ENDURANCE TRAINING IS ASSOCIATED WITH REDUCED NEUROMUSCULAR ACTIVITY", "year": "2001"}, "source": "citations", "id_citations": "oIbxZhIAAAAJ:RGFaLdJalmkC", "citedby": "0"}, {"bib": {"title": "220 Strength training during bed rest attenuates the decline in steadiness", "year": "2001"}, "source": "citations", "id_citations": "oIbxZhIAAAAJ:NMxIlDl6LWMC", "citedby": "0"}, {"bib": {"title": "(E71012) Alternate Muscular Activity in Quadriceps Muscle at Various Force Contraction Levels", "year": "1999"}, "source": "citations", "id_citations": "oIbxZhIAAAAJ:EUQCXRtRnyEC", "citedby": "0"}, {"bib": {"title": "Oxygen deficit and augmented motor unit activity at the onset of dynamic exercise", "year": "1994"}, "source": "citations", "id_citations": "oIbxZhIAAAAJ:CHSYGLWDkRkC", "citedby": "0"}, {"bib": {"title": "COMPUTER-AIDED IMPEDANCE CARDIOGRAPHY FOR CONTINUOUS CARDIAC OUTPUT MEASUREMENT DURING MAXIMAL EXERCISE: 418", "year": "1992"}, "source": "citations", "id_citations": "oIbxZhIAAAAJ:RYcK_YlVTxYC", "citedby": "0"}, {"bib": {"title": "COPPER WIRE OBTAINED FROM CONTINUOUS CASTING WITH HEATING MOULD", "year": "1987"}, "source": "citations", "id_citations": "oIbxZhIAAAAJ:N5tVd3kTz84C", "citedby": "0"}, {"bib": {"title": "physiological Profile In A Triathlon Race Performed At Anaerobic Threshold: 41", "year": "1980"}, "source": "citations", "id_citations": "oIbxZhIAAAAJ:3s1wT3WcHBgC", "citedby": "0"}, {"bib": {"title": "the Importance Of Timing Of Exercise Stimuli On Ventilatory Responses: 122", "year": "1980"}, "source": "citations", "id_citations": "oIbxZhIAAAAJ:35N4QoGY0k4C", "citedby": "0"}, {"bib": {"title": "blood Lactate Kinetics Related To Ventilatory Threshold During Incremental Exercise: 144", "year": "1980"}, "source": "citations", "id_citations": "oIbxZhIAAAAJ:lSLTfruPkqcC", "citedby": "0"}, {"bib": {"title": "Musculoskeletal Science and Practice"}, "source": "citations", "id_citations": "oIbxZhIAAAAJ:JQOojiI6XY0C", "citedby": "0"}, {"bib": {"title": "THE EFFECT OF COMPRESSION PANTS ON POSTURAL STEADINESS BEFORE AND AFTER TIRING EXERCISE"}, "source": "citations", "id_citations": "oIbxZhIAAAAJ:UHK10RUVsp4C", "citedby": "0"}]}